hardware_address-0.2.0.dist-info/METADATA
hardware_address-0.2.0.dist-info/WHEEL
hardware_address/__init__.py
hardware_address/hardware_address.abi3.so
hardware_address-0.2.0.dist-info/RECORD
