Metadata-Version: 2.4
Name: hardware-address
Version: 0.2.0
Classifier: Development Status :: 4 - Beta
Classifier: Intended Audience :: Developers
Classifier: License :: OSI Approved :: MIT License
Classifier: License :: OSI Approved :: Apache Software License
Classifier: Programming Language :: Python :: 3
Classifier: Programming Language :: Python :: 3.8
Classifier: Programming Language :: Python :: 3.9
Classifier: Programming Language :: Python :: 3.10
Classifier: Programming Language :: Python :: 3.11
Classifier: Programming Language :: Python :: 3.12
Classifier: Programming Language :: Python :: 3.13
Classifier: Programming Language :: Rust
Classifier: Programming Language :: Python :: Implementation :: CPython
Classifier: Programming Language :: Python :: Implementation :: PyPy
Classifier: Topic :: Software Development :: Libraries
Classifier: Topic :: System :: Networking
Requires-Dist: pytest>=7.0 ; extra == 'test'
Provides-Extra: test
Summary: IEEE 802 MAC-48, EUI-48, EUI-64, or a 20-octet IP over InfiniBand link-layer addresses
Keywords: mac-address,eui64,eui48,hardware-address,network,infiniband,ieee802
Author-email: Al Liu <scygliu1@gmail.com>
License: MIT OR Apache-2.0
Requires-Python: >=3.8
Project-URL: Homepage, https://github.com/al8n/hardware-address
Project-URL: Repository, https://github.com/al8n/hardware-address
Project-URL: Documentation, https://docs.rs/hardware-address
Project-URL: Bug Tracker, https://github.com/al8n/hardware-address/issues
Project-URL: Source Code, https://github.com/al8n/hardware-address
